{"1009":"Bayem","1010":"Semawung Kembaran","1014":"Semawung Daleman","1015":"Bandung","1016":"Kutoarjo","1017":"Katerban","2001":"Kebondalem","2002":"Tuntungpait","2003":"Kiyangkongrejo","2004":"Suren","2005":"Karangwuluh","2006":"Purwosari","2007":"Kepuh","2008":"Majir","2011":"Kuwurejo","2012":"Pringgowijayan","2013":"Sidarum","2018":"Pacor","2019":"Tunggorono","2020":"Tepus Kulon","2021":"Sokoharjo","2022":"Kemadu Lor","2023":"Kaligesing","2024":"Tepus Wetan","2025":"Wirun","2026":"Karangrejo","2027":"Tursino"}