{"1015":"Punggursugih","1018":"Ngawen","2001":"Rowobungkul","2002":"Gedebeg","2003":"Sambonganyar","2004":"Kendayaan","2005":"Plumbon","2006":"Bergolo","2007":"Bandungrojo","2008":"Kedungsatriyan","2009":"Karangtengah","2010":"Jetakwanger","2011":"Sumberejo","2012":"Sendangagung","2013":"Talokwohmojo","2014":"Trembulrejo","2016":"Gondang","2017":"Sendangrejo","2019":"Semawur","2020":"Bradag","2021":"Gotputuk","2022":"Berbak","2023":"Sarimulyo","2024":"Sendangmulyo","2025":"Wantilgung","2026":"Bogowanti","2027":"Sambongrejo","2028":"Srigading","2029":"Karangjong"}