{"2001":"Arul Gele","2002":"Arul Kumer","2003":"Burni Bius","2004":"Genting Gerbang","2005":"Gunung Singit","2007":"Pepayungan Angkup","2008":"Remesen","2009":"Rutih","2010":"Semelit Mutiara","2012":"Wih Porak","2013":"Wih Bakong","2014":"Wihni Durin","2016":"Arul Putih","2017":"Arul Relem","2018":"Burni Bius Baru","2019":"Jerata","2022":"Paya Beke","2023":"Paya Pelu","2026":"Rebe Gedung","2027":"Reremal","2029":"Senehen","2030":"Simpang Kemili","2031":"Tenebuk Kampung Baru","2032":"Terang Engon","2033":"Wih Pesam","2034":"Bius Utama","2035":"Meker Indah","2036":"Mulie Jadi","2037":"Wih Bersih","2038":"Wih Sagi Indah","2039":"Arul Kumer Barat","2040":"Arul Kumer Timur","2041":"Arul Kumer Selatan"}